[
  {
    "id": "old-brand-agei",
    "name": "淡水老牌阿給",
    "category": "snack",
    "address": "新北市淡水區真理街6-1號",
    "googleMapsUrl": "https://maps.google.com/?q=淡水老牌阿給+真理街",
    "lat": 25.1748,
    "lng": 121.4368,
    "priceRange": "$",
    "avgPrice": 50,
    "tags": ["一人", "外帶", "雨天OK"],
    "hours": "05:00-14:00",
    "closedOn": "週一",
    "queueStatus": "假日排15分",
    "recommended": ["招牌阿給", "魚丸湯"],
    "review": "1965年創業的阿給創始店，魚漿封口鮮嫩，不加醬也好吃",
    "coverEmoji": "🫓",
    "updatedAt": "2026-03-22",
    "isSampleData": false
  },
  {
    "id": "wenhua-agei",
    "name": "淡水文化阿給",
    "category": "snack",
    "address": "新北市淡水區真理街6-4號",
    "googleMapsUrl": "https://maps.google.com/?q=淡水文化阿給+真理街",
    "lat": 25.1749,
    "lng": 121.4367,
    "priceRange": "$",
    "avgPrice": 55,
    "tags": ["一人", "外帶", "聚餐"],
    "hours": "06:30-18:00",
    "closedOn": "無",
    "queueStatus": "假日排15分",
    "recommended": ["周杰倫套餐", "阿給加蛋"],
    "review": "周杰倫加持的阿給名店，套餐組合CP值高，觀光客最愛",
    "coverEmoji": "🍢",
    "updatedAt": "2026-03-22",
    "isSampleData": false
  },
  {
    "id": "apo-iron-egg",
    "name": "阿婆鐵蛋",
    "category": "snack",
    "address": "新北市淡水區中正路135-1號",
    "googleMapsUrl": "https://maps.google.com/?q=阿婆鐵蛋+淡水",
    "lat": 25.1697,
    "lng": 121.4401,
    "priceRange": "$",
    "avgPrice": 60,
    "tags": ["外帶", "一人"],
    "hours": "09:00-22:00",
    "closedOn": "無",
    "queueStatus": "平日不排",
    "recommended": ["原味鐵蛋", "辣味鐵蛋"],
    "review": "經營超過40年的鐵蛋老店，越嚼越香的淡水代表伴手禮",
    "coverEmoji": "🥚",
    "updatedAt": "2026-03-22",
    "isSampleData": false
  },
  {
    "id": "kekou-fishball",
    "name": "淡水可口魚丸",
    "category": "snack",
    "address": "新北市淡水區中正路232號",
    "googleMapsUrl": "https://maps.google.com/?q=淡水可口魚丸+中正路",
    "lat": 25.1707,
    "lng": 121.4389,
    "priceRange": "$",
    "avgPrice": 55,
    "tags": ["一人", "外帶", "雨天OK"],
    "hours": "09:00-20:00",
    "closedOn": "無",
    "queueStatus": "平日不排",
    "recommended": ["包肉魚丸湯", "魚酥"],
    "review": "淡水老街老字號魚丸店，手工魚丸肉味十足，魚酥也必買",
    "coverEmoji": "🐟",
    "updatedAt": "2026-03-22",
    "isSampleData": false
  },
  {
    "id": "linji-meatball",
    "name": "林記肉圓",
    "category": "snack",
    "address": "新北市淡水區中正路177號",
    "googleMapsUrl": "https://maps.google.com/?q=林記肉圓+淡水+中正路",
    "lat": 25.1702,
    "lng": 121.4395,
    "priceRange": "$",
    "avgPrice": 50,
    "tags": ["一人", "外帶", "雨天OK"],
    "hours": "10:30-19:30",
    "closedOn": "週一",
    "queueStatus": "平日不排",
    "recommended": ["油泡肉圓", "貢丸湯"],
    "review": "油泡肉圓皮Q內餡扎實不膩口，手工貢丸肉味濃厚",
    "coverEmoji": "🧆",
    "updatedAt": "2026-03-22",
    "isSampleData": false
  },
  {
    "id": "baiyu-wonton",
    "name": "百葉溫州餛飩",
    "category": "noodles",
    "address": "新北市淡水區中正路117號",
    "googleMapsUrl": "https://maps.google.com/?q=百葉溫州餛飩+淡水",
    "lat": 25.1693,
    "lng": 121.4405,
    "priceRange": "$",
    "avgPrice": 80,
    "tags": ["一人", "聚餐", "雨天OK"],
    "hours": "10:00-21:00",
    "closedOn": "無",
    "queueStatus": "假日排15分",
    "recommended": ["餛飩湯", "烤雞腿"],
    "review": "50年老店，周杰倫必點餛飩湯加烤雞腿的經典組合",
    "coverEmoji": "🥟",
    "updatedAt": "2026-03-22",
    "isSampleData": false
  },
  {
    "id": "axiang-quail-egg",
    "name": "阿香蝦捲烤鳥蛋",
    "category": "snack",
    "address": "新北市淡水區中正路230號",
    "googleMapsUrl": "https://maps.google.com/?q=阿香蝦捲烤鳥蛋+淡水",
    "lat": 25.1706,
    "lng": 121.4390,
    "priceRange": "$",
    "avgPrice": 50,
    "tags": ["一人", "外帶"],
    "hours": "11:00-20:00",
    "closedOn": "無",
    "queueStatus": "假日排30分+",
    "recommended": ["魩仔魚烤鳥蛋", "蝦捲"],
    "review": "每顆鳥蛋包覆50隻以上魩仔魚，老街排隊王",
    "coverEmoji": "🥚",
    "updatedAt": "2026-03-22",
    "isSampleData": false
  },
  {
    "id": "yuanwei-cake",
    "name": "源味本舖古早味蛋糕",
    "category": "dessert",
    "address": "新北市淡水區中正路249號",
    "googleMapsUrl": "https://maps.google.com/?q=源味本舖+淡水",
    "lat": 25.1710,
    "lng": 121.4385,
    "priceRange": "$",
    "avgPrice": 120,
    "tags": ["外帶", "一人"],
    "hours": "10:00-19:00",
    "closedOn": "無",
    "queueStatus": "假日排15分",
    "recommended": ["原味古早味蛋糕", "起司口味"],
    "review": "剛出爐的蛋糕體超綿密入口即化，起司口味鹹甜美味",
    "coverEmoji": "🍰",
    "updatedAt": "2026-03-22",
    "isSampleData": false
  },
  {
    "id": "maji-grandma",
    "name": "麻吉奶奶鮮奶麻糬",
    "category": "dessert",
    "address": "新北市淡水區中正路183號",
    "googleMapsUrl": "https://maps.google.com/?q=麻吉奶奶鮮奶麻糬+淡水",
    "lat": 25.1703,
    "lng": 121.4394,
    "priceRange": "$",
    "avgPrice": 45,
    "tags": ["外帶", "一人"],
    "hours": "11:00-19:00",
    "closedOn": "週二",
    "queueStatus": "假日排15分",
    "recommended": ["鮮奶麻糬", "花生麻糬"],
    "review": "純手工鮮奶麻糬不加糯米，簡單美味好消化",
    "coverEmoji": "🍡",
    "updatedAt": "2026-03-22",
    "isSampleData": false
  },
  {
    "id": "xinjiancheng",
    "name": "新建成餅店",
    "category": "dessert",
    "address": "新北市淡水區公明街42號",
    "googleMapsUrl": "https://maps.google.com/?q=新建成餅店+淡水",
    "lat": 25.1695,
    "lng": 121.4403,
    "priceRange": "$",
    "avgPrice": 100,
    "tags": ["外帶"],
    "hours": "08:00-22:00",
    "closedOn": "無",
    "queueStatus": "平日不排",
    "recommended": ["三色糕", "綠豆椪"],
    "review": "淡水百年老餅舖，傳統糕餅伴手禮首選",
    "coverEmoji": "🥮",
    "updatedAt": "2026-03-22",
    "isSampleData": false
  },
  {
    "id": "la-villa-danshui",
    "name": "La Villa Danshui",
    "category": "restaurant",
    "address": "新北市淡水區中正路233號2樓",
    "googleMapsUrl": "https://maps.google.com/?q=La+Villa+Danshui+淡水",
    "lat": 25.1752,
    "lng": 121.4330,
    "priceRange": "$$$",
    "avgPrice": 600,
    "tags": ["約會", "聚餐", "雨天OK"],
    "hours": "11:30-21:30",
    "closedOn": "無",
    "queueStatus": "建議訂位",
    "recommended": ["義大利麵", "牛排"],
    "review": "純白建築配落地窗，傍晚夕陽河景超浪漫的義式餐廳",
    "coverEmoji": "🍝",
    "updatedAt": "2026-03-22",
    "isSampleData": false
  },
  {
    "id": "lb-cafe",
    "name": "淡水長堤 LB Cafe",
    "category": "cafe",
    "address": "新北市淡水區中正路233-3號",
    "googleMapsUrl": "https://maps.google.com/?q=淡水長堤+LB+Cafe",
    "lat": 25.1700,
    "lng": 121.4392,
    "priceRange": "$$",
    "avgPrice": 250,
    "tags": ["約會", "聚餐", "雨天OK"],
    "hours": "11:00-22:00",
    "closedOn": "無",
    "queueStatus": "假日排15分",
    "recommended": ["漢堡排", "河景下午茶"],
    "review": "2樓戶外區無敵河景視野，看夕陽配咖啡的經典選擇",
    "coverEmoji": "☕",
    "updatedAt": "2026-03-22",
    "isSampleData": false
  },
  {
    "id": "ancre-cafe",
    "name": "Ancre cafe 安克黑咖啡",
    "category": "cafe",
    "address": "新北市淡水區中正路330號2樓",
    "googleMapsUrl": "https://maps.google.com/?q=安克黑咖啡+淡水",
    "lat": 25.1715,
    "lng": 121.4380,
    "priceRange": "$$",
    "avgPrice": 200,
    "tags": ["約會", "一人", "雨天OK"],
    "hours": "12:00-20:00",
    "closedOn": "週三",
    "queueStatus": "窗邊位常滿",
    "recommended": ["手沖咖啡", "布丁"],
    "review": "河景第一排的文青咖啡廳，窗邊位置超搶手",
    "coverEmoji": "☕",
    "updatedAt": "2026-03-22",
    "isSampleData": false
  },
  {
    "id": "shuiwan-bali",
    "name": "水灣Bali景觀餐廳榕堤店",
    "category": "restaurant",
    "address": "新北市淡水區中正路229號",
    "googleMapsUrl": "https://maps.google.com/?q=水灣Bali+榕堤+淡水",
    "lat": 25.1753,
    "lng": 121.4326,
    "priceRange": "$$$",
    "avgPrice": 500,
    "tags": ["約會", "聚餐", "雨天OK", "有停車"],
    "hours": "11:00-22:00",
    "closedOn": "無",
    "queueStatus": "建議訂位",
    "recommended": ["峇里島風味套餐", "景觀下午茶"],
    "review": "峇里島villa風情搭配淡水河景，約會聚餐氣氛滿分",
    "coverEmoji": "🌴",
    "updatedAt": "2026-03-22",
    "isSampleData": false
  },
  {
    "id": "pallet-bistro",
    "name": "Pallet Bistro 木棧板餐廳",
    "category": "restaurant",
    "address": "新北市淡水區中正路330號",
    "googleMapsUrl": "https://maps.google.com/?q=Pallet+Bistro+淡水",
    "lat": 25.1714,
    "lng": 121.4382,
    "priceRange": "$$",
    "avgPrice": 350,
    "tags": ["約會", "聚餐", "雨天OK"],
    "hours": "11:30-21:00",
    "closedOn": "週二",
    "queueStatus": "假日排15分",
    "recommended": ["手工Pizza", "燉飯"],
    "review": "老街上的歐風餐酒館，木質調裝潢配河景很有味道",
    "coverEmoji": "🍕",
    "updatedAt": "2026-03-22",
    "isSampleData": false
  },
  {
    "id": "erlou-tamsui",
    "name": "貳樓淡水站前店",
    "category": "restaurant",
    "address": "新北市淡水區中正東路二段68號6樓",
    "googleMapsUrl": "https://maps.google.com/?q=貳樓+淡水站前店",
    "lat": 25.1680,
    "lng": 121.4420,
    "priceRange": "$$",
    "avgPrice": 380,
    "tags": ["約會", "聚餐", "親子", "雨天OK"],
    "hours": "09:00-22:00",
    "closedOn": "無",
    "queueStatus": "假日排15分",
    "recommended": ["早午餐拼盤", "鬆餅"],
    "review": "捷運站對面大都會廣場6樓，眺望觀音山的絕佳視野",
    "coverEmoji": "🍳",
    "updatedAt": "2026-03-22",
    "isSampleData": false
  },
  {
    "id": "meet-europa",
    "name": "米特食堂 MeetEuropa",
    "category": "noodles",
    "address": "新北市淡水區英專路50巷6號",
    "googleMapsUrl": "https://maps.google.com/?q=米特食堂+MeetEuropa+淡水",
    "lat": 25.1670,
    "lng": 121.4440,
    "priceRange": "$",
    "avgPrice": 180,
    "tags": ["一人", "聚餐", "雨天OK"],
    "hours": "11:30-21:00",
    "closedOn": "週日",
    "queueStatus": "平日不排",
    "recommended": ["白酒蛤蜊義大利麵", "牛排套餐"],
    "review": "隱身英專夜市旁的超值義式料理，學生和上班族最愛",
    "coverEmoji": "🍝",
    "updatedAt": "2026-03-22",
    "isSampleData": false
  },
  {
    "id": "tianguo-hotpot",
    "name": "天鍋宴淡水店",
    "category": "hotpot",
    "address": "新北市淡水區觀海路91號",
    "googleMapsUrl": "https://maps.google.com/?q=天鍋宴+淡水店",
    "lat": 25.1780,
    "lng": 121.4150,
    "priceRange": "$$",
    "avgPrice": 450,
    "tags": ["聚餐", "約會", "親子", "雨天OK", "有停車"],
    "hours": "11:00-22:00",
    "closedOn": "無",
    "queueStatus": "建議訂位",
    "recommended": ["海鮮鍋", "牛肉鍋"],
    "review": "漁人碼頭旁的景觀火鍋，菜盤和冰淇淋吃到飽",
    "coverEmoji": "🫕",
    "updatedAt": "2026-03-22",
    "isSampleData": false
  },
  {
    "id": "guodon-shabu",
    "name": "鍋董日式涮涮鍋",
    "category": "hotpot",
    "address": "新北市淡水區北新路6號",
    "googleMapsUrl": "https://maps.google.com/?q=鍋董日式涮涮鍋+淡水",
    "lat": 25.1665,
    "lng": 121.4445,
    "priceRange": "$$",
    "avgPrice": 350,
    "tags": ["一人", "聚餐", "雨天OK"],
    "hours": "11:00-01:30",
    "closedOn": "無",
    "queueStatus": "平日不排",
    "recommended": ["海鮮鍋", "自製冰淇淋"],
    "review": "營業到凌晨的深夜火鍋，無限量飲料和冰淇淋超佛心",
    "coverEmoji": "🍲",
    "updatedAt": "2026-03-22",
    "isSampleData": false
  },
  {
    "id": "qiancao-dessert",
    "name": "淺草職人手作甜品鋪",
    "category": "drinks",
    "address": "新北市淡水區中正路185號",
    "googleMapsUrl": "https://maps.google.com/?q=淺草職人手作甜品鋪+淡水",
    "lat": 25.1704,
    "lng": 121.4393,
    "priceRange": "$",
    "avgPrice": 65,
    "tags": ["一人", "外帶"],
    "hours": "11:00-19:00",
    "closedOn": "週一",
    "queueStatus": "平日不排",
    "recommended": ["手工豆花", "芋圓甜湯"],
    "review": "天然手作配料搭配豆花甜湯，冬暖夏涼的古早味甜品",
    "coverEmoji": "🍧",
    "updatedAt": "2026-03-22",
    "isSampleData": false
  }
]
